oglob/__init__.py
oglob-0.1.0.dist-info/LICENSE
oglob-0.1.0.dist-info/METADATA
oglob-0.1.0.dist-info/WHEEL
oglob-0.1.0.dist-info/RECORD
